klogs/__init__.py
klogs/cli.py
klogs/lib.py
klogs-3.0.0.dist-info/METADATA
klogs-3.0.0.dist-info/WHEEL
klogs-3.0.0.dist-info/entry_points.txt
klogs-3.0.0.dist-info/top_level.txt
klogs-3.0.0.dist-info/RECORD
