Metadata-Version: 2.1
Name: klogs
Version: 3.0.0
Summary: UNKNOWN
Home-page: UNKNOWN
Author: UNKNOWN
Author-email: UNKNOWN
License: Not Open Source
Platform: UNKNOWN
Requires-Dist: click (>=7.0)
